perf_timer/__init__.py
perf_timer/_histogram.py
perf_timer/_impl.py
perf_timer/_trio.py
perf_timer/_version.py
perf_timer-0.2.2.dist-info/LICENSE
perf_timer-0.2.2.dist-info/METADATA
perf_timer-0.2.2.dist-info/WHEEL
perf_timer-0.2.2.dist-info/top_level.txt
perf_timer-0.2.2.dist-info/RECORD
