Metadata-Version: 2.1
Name: perf-timer
Version: 0.2.2
Summary: An indispensable performance timer for Python
Home-page: https://github.com/belm0/perf-timer
Author: John Belmonte
Author-email: john@neggie.net
License: MIT
Platform: UNKNOWN
Classifier: Development Status :: 3 - Alpha
Classifier: Intended Audience :: Developers
Classifier: License :: OSI Approved :: MIT License
Classifier: Programming Language :: Python :: 3 :: Only
Classifier: Programming Language :: Python :: 3.7
Classifier: Programming Language :: Python :: 3.8
Classifier: Programming Language :: Python :: 3.9
Classifier: Framework :: Trio
Requires-Python: >=3.7
